[
    {
        "ParameterKey": "ClientID",
        "ParameterValue": "00000000000-0000000000-000000"
    },
    {
        "ParameterKey": "ConfigRules",
        "ParameterValue": "True"
    },
    {
        "ParameterKey": "DeployAWSConfigSupport",
        "ParameterValue": "True"
    },
    {
        "ParameterKey": "EnableAWSConfigRecorder",
        "ParameterValue": "True"
    },
    {
        "ParameterKey": "Grant",
        "ParameterValue": "password"
    },
    {
        "ParameterKey": "IncludeGlobalResourceTypes",
        "ParameterValue": "False"
    },
    {
        "ParameterKey": "Password",
        "ParameterValue": "CSDAdmin"
    },
    {
        "ParameterKey": "QSS3BucketName",
        "ParameterValue": "$[taskcat_autobucket]"
    },
    {
        "ParameterKey": "QSS3KeyPrefix",
        "ParameterValue": "quickstart-cherwell/"
    },
    {
        "ParameterKey": "Url",
        "ParameterValue": "http://yourserver.com"
    },
    {
        "ParameterKey": "Username",
        "ParameterValue": "CSDAdmin"
    }
]